highcharts/__init__.py
highcharts/ipynb.py
highcharts/version.py
highcharts/highcharts/__init__.py
highcharts/highcharts/common.py
highcharts/highcharts/highchart_types.py
highcharts/highcharts/highcharts.py
highcharts/highcharts/options.py
highcharts/highcharts/templates/base.html
highcharts/highcharts/templates/content.html
highcharts/highcharts/templates/page.html
highcharts/highcharts/templates/test.html
highcharts/highmaps/__init__.py
highcharts/highmaps/common.py
highcharts/highmaps/highmap_helper.py
highcharts/highmaps/highmap_types.py
highcharts/highmaps/highmaps.py
highcharts/highmaps/options.py
highcharts/highmaps/templates/base.html
highcharts/highmaps/templates/content.html
highcharts/highmaps/templates/page.html
highcharts/highmaps/templates/test.html
highcharts/highstock/__init__.py
highcharts/highstock/common.py
highcharts/highstock/highstock.py
highcharts/highstock/highstock_helper.py
highcharts/highstock/highstock_types.py
highcharts/highstock/options.py
highcharts/highstock/templates/base.html
highcharts/highstock/templates/content.html
highcharts/highstock/templates/page.html
highcharts/highstock/templates/test.html
python_highcharts_excentis-0.4.3b20230324.dist-info/LICENSE
python_highcharts_excentis-0.4.3b20230324.dist-info/METADATA
python_highcharts_excentis-0.4.3b20230324.dist-info/WHEEL
python_highcharts_excentis-0.4.3b20230324.dist-info/top_level.txt
python_highcharts_excentis-0.4.3b20230324.dist-info/RECORD
