Metadata-Version: 2.1
Name: python-highcharts-excentis
Version: 0.4.3b20230324
Summary: Python Highcharts wrapper
Home-page: https://github.com/excentis/python-highcharts
Author: Kyper Developers
Author-email: developers@kyperdata.com
Maintainer: Excentis Software
Maintainer-email: support@excentis.com
License: UNKNOWN
Keywords: python,ipython,highcharts,chart,visualization,graph,javascript,html
Platform: UNKNOWN
Classifier: Framework :: IPython
Classifier: Intended Audience :: Developers
Classifier: Intended Audience :: Financial and Insurance Industry
Classifier: Intended Audience :: Science/Research
Classifier: License :: OSI Approved :: MIT License
Classifier: Programming Language :: Python
Classifier: Programming Language :: Python :: 3
Requires-Dist: Jinja2
Requires-Dist: future
